sdk/__init__.py
sdk/collector.py
sdk/middleware.py
kusho_capture-0.1.0.dist-info/LICENSE
kusho_capture-0.1.0.dist-info/METADATA
kusho_capture-0.1.0.dist-info/WHEEL
kusho_capture-0.1.0.dist-info/top_level.txt
kusho_capture-0.1.0.dist-info/RECORD
