Metadata-Version: 2.1
Name: kusho-capture
Version: 0.1.0
Summary: HTTP traffic capture middleware for Python web applications
Home-page: https://github.com/kusho-co/kusho-capture
Author: KushoAI
Author-email: support@kusho.co
Keywords: http,middleware,traffic capture,api testing,monitoring,debugging
Classifier: Development Status :: 3 - Alpha
Classifier: Intended Audience :: Developers
Classifier: License :: OSI Approved :: MIT License
Classifier: Programming Language :: Python :: 3
Classifier: Programming Language :: Python :: 3.7
Classifier: Programming Language :: Python :: 3.8
Classifier: Programming Language :: Python :: 3.9
Classifier: Programming Language :: Python :: 3.10
Classifier: Framework :: FastAPI
Classifier: Framework :: Flask
Classifier: Framework :: Django
Classifier: Topic :: Software Development :: Testing
Classifier: Topic :: Software Development :: Libraries :: Python Modules
Requires-Python: >=3.7
License-File: LICENSE
Requires-Dist: requests>=2.25.0
Provides-Extra: fastapi
Requires-Dist: fastapi>=0.65.0; extra == "fastapi"
Provides-Extra: flask
Requires-Dist: flask>=2.0.0; extra == "flask"
Provides-Extra: django
Requires-Dist: django>=3.2; extra == "django"
